README.rst
setup.cfg
setup.py
silversalts/__init__.py
silversalts.egg-info/PKG-INFO
silversalts.egg-info/SOURCES.txt
silversalts.egg-info/dependency_links.txt
silversalts.egg-info/requires.txt
silversalts.egg-info/top_level.txt
silversalts/api/__init__.py
silversalts/api/crypter.py
silversalts/api/packager.py