Metadata-Version: 1.1
Name: silversalts
Version: 0.1.2
Summary: A SilverSalts Python Project
Home-page: https://api.silversalts.com
Author: IUTU Inc.
Author-email: contact@silversalts.com
License: MIT
Keywords: image recognition,ocr
Platform: UNKNOWN
Classifier: Development Status :: 5 - Production/Stable
Classifier: Intended Audience :: Developers
Classifier: Topic :: Software Development :: Libraries
Classifier: License :: OSI Approved :: MIT License
Classifier: Programming Language :: Python :: 2
Classifier: Programming Language :: Python :: 2.7
Classifier: Programming Language :: Python :: 3
Classifier: Programming Language :: Python :: 3.3
Classifier: Programming Language :: Python :: 3.4
Classifier: Programming Language :: Python :: 3.5
